mtress/__init__.py
mtress/_abstract_component.py
mtress/_constants.py
mtress/_data_handler.py
mtress/_interfaces.py
mtress/_location.py
mtress/_meta_model.py
mtress/_oemof_storage_multiplexer.py
mtress/_run_mtress.py
mtress/_solph_model.py
mtress/_helpers/__init__.py
mtress/_helpers/_array_cast.py
mtress/_helpers/_results.py
mtress/_helpers/_util.py
mtress/_helpers/_visualization.py
mtress/carriers/__init__.py
mtress/carriers/_abstract_carrier.py
mtress/carriers/_electricity.py
mtress/carriers/_gas.py
mtress/carriers/_heat.py
mtress/demands/__init__.py
mtress/demands/_abstract_demand.py
mtress/demands/_electricity.py
mtress/demands/_fixed_temperature_heat.py
mtress/demands/_gas.py
mtress/physics/__init__.py
mtress/physics/_constants.py
mtress/physics/_gas_definition.py
mtress/physics/_helper_functions.py
mtress/technologies/__init__.py
mtress/technologies/_abstract_homogenous_storage.py
mtress/technologies/_abstract_technology.py
mtress/technologies/_battery_storage.py
mtress/technologies/_chp.py
mtress/technologies/_compressor.py
mtress/technologies/_electrolyser.py
mtress/technologies/_ev.py
mtress/technologies/_fuel_cell.py
mtress/technologies/_heat_exchanger.py
mtress/technologies/_heat_pump.py
mtress/technologies/_heater.py
mtress/technologies/_renewable_electricity_source.py
mtress/technologies/_slack.py
mtress/technologies/_heat_storage/__init__.py
mtress/technologies/_heat_storage/_abstract_heat_storage.py
mtress/technologies/_heat_storage/_multi_layer_storage.py
mtress/technologies/_pressure_storage/__init__.py
mtress/technologies/_pressure_storage/_gas_storage.py
mtress/technologies/_pressure_storage/_h2_storage.py
mtress/technologies/grid_connection/__init__.py
mtress/technologies/grid_connection/_abstract_gas_grid_connection.py
mtress/technologies/grid_connection/_abstract_grid_connection.py
mtress/technologies/grid_connection/_electricity.py
mtress/technologies/grid_connection/_gas.py
mtress/technologies/grid_connection/_heat.py
mtress-26.1.26.dist-info/licenses/LICENSE
mtress-26.1.26.dist-info/WHEEL
mtress-26.1.26.dist-info/METADATA
mtress-26.1.26.dist-info/RECORD
