Metadata-Version: 2.4
Name: mtress
Version: 26.1.26
Summary: Energy System Model Template
Author-email: "Deutsches Zentrum für Luft- und Raumfahrt e.V. (DLR)" <patrik.schoenfeldt@dlr.de>
Requires-Python: >=3.10
Classifier: Development Status :: 3 - Alpha
Classifier: Intended Audience :: Developers
Classifier: Intended Audience :: Science/Research
Classifier: License :: OSI Approved :: MIT License
Classifier: Operating System :: Unix
Classifier: Operating System :: POSIX
Classifier: Operating System :: Microsoft :: Windows
Classifier: Operating System :: MacOS
Classifier: Operating System :: OS Independent
Classifier: Programming Language :: Python
Classifier: Programming Language :: Python :: 3
Classifier: Topic :: Utilities
License-File: LICENSE
Requires-Dist: graphviz
Requires-Dist: oemof.network>=0.5.2a1
Requires-Dist: oemof.solph>=0.6.2a2
Requires-Dist: oemof.thermal>=0.0.9a1
Requires-Dist: pandas>=1.3.4
Requires-Dist: PyYAML>=6.0
Requires-Dist: numpy>=2.2.0
Requires-Dist: jsonschema
Requires-Dist: setuptools>=59.1.1
Requires-Dist: tox
Requires-Dist: dash
Requires-Dist: dash-cytoscape
